{
    "t": "tao",
    "k": "không",
    "kh": "không",
    "ko": "không",
    "e": "em",
    "vs": "với",
    "v": "vậy",
    "mn": "mọi người",
    "m": "mày",
    "đc": "được",
    "dc": "được",
    "z": "vậy",
    "j": "gì",
    "ng": "người",
    "ngta": "người ta",
    "mk": "mình",
    "mik": "mình",
    "r": "rồi",
    "hn": "hà nội",
    "sg": "sài gòn",
    "vn": "việt nam",
    "ny": "người yêu",
    "nyc": "người yêu cũ",
    "h": "giờ",
    "b": "bạn",
    "bn": "bạn",
    "cx": "cũng",
    "thik": "thích",
    "iu": "yêu",
    "ak": "à",
    "uk": "ừ",
    "c": "chị",
    "cj": "chị",
    "lm": "làm",
    "qtrong": "quan trọng",
    "vkl": "vãi cả l**",
    "vl": "vãi l**",
    "dcm": "địt con mẹ",
    "clm": "cái l** má",
    "dell": "đéo",
    "đm": "địt mẹ",
    "vch": "vãi chưởng",
    "bt": "biết",
    "kbt": "không biết",
    "ntn": "như thế này",
    "đag": "đang",
    "tr": "trời",
    "lun": "luôn",
    "wa": "quá",
    "qa": "quá",
    "nma": "nhưng mà",
    "nhma": "nhưng mà",
    "ck": "chồng",
    "vk": "vợ",
    "bame": "ba mẹ",
    "csgt": "cảnh sát giao thông",
    "oto": "ô tô",
    "bs": "bác sĩ",
    "sn": "sinh nhật",
    "cmt": "bình luận",
    "rep": "trả lời",
    "ib": "nhắn tin",
    "ad": "admin",
    "add": "admin",
    "shop": "cửa hàng",
    "s": "sao",
    "tht": "thật",
    "thui": "thôi",
    "n": "nó",
    "ae": "anh em",
    "g": "gì",
    "zậy": "vậy",
    "zay": "vậy",
    "th": "thôi",
    "đ": "đéo",
    "cug": "cũng",
    "đug": "đúng",
    "bth": "bình thường",
    "p": "phải",
    "fai": "phải",
    "hok": "không",
    "hong": "không",
    "hông": "không",
    "hẻ": "hả",
    "rùi": "rồi",
    "dọng": "giọng",
    "xl": "xin lỗi",
    "dk": "được",
    "đk": "được",
    "bít": "biết",
    "bik": "biết",
    "bit": "biết",
    "ch": "chưa",
    "nv": "như vậy",
    "bh": "bây giờ",
    "bao h": "bao giờ",
    "j z tr": "gì vậy trời",
    "keke": "cười",
    "kkk": "cười",
    "hic": "khóc",
    "huhu": "khóc",
    "haiz": "haizz",
    "haizz": "thở dài",
    "u là tr": "trời ơi",
    "u là trời": "trời ơi",
    "zậy tr": "vậy trời",
    "gì z tr": "gì vậy trời",
    "gì zậy trời": "gì vậy trời",
    "khum": "không",
    "khum bít": "không biết",
    "khum bíc": "không biết",
    "chằm zn": "trầm cảm",
    "trầm kẽm": "trầm cảm",
    "xu cà na": "xui xẻo",
    "xu": "xui",
    "mãi mận": "tuyệt vời",
    "keo lì": "tuyệt vời",
    "báo quá báo": "phá hoại quá",
    "báo quá": "phá hoại quá",
    "báo thủ": "người phá hoại",
    "ét o ét": "cứu với",
    "sos": "cứu với",
    "ô dề": "làm lố",
    "ô dề quá": "lố lăng quá",
    "cừi ẻ": "buồn cười",
    "cười ẻ": "buồn cười",
    "cười ỉa": "buồn cười quá",
    "hề vãi": "hài hước quá",
    "hề hước": "hài hước",
    "chúa tể": "bậc thầy",
    "thánh": "người rất giỏi",
    "out trình": "trình độ cao hơn hẳn",
    "ao trình": "trình độ cao hơn hẳn",
    "đỉnh kout": "đỉnh cao",
    "đỉnh chóp": "tuyệt vời",
    "gét gô": "đi thôi",
    "trân quý": "trân trọng",
    "đã cái nư": "thoả mãn",
    "đã cái nết": "thỏa mãn",
    "lươn lẹo": "không trung thực",
    "lươn": "gian dối",
    "tấm chiếu mới": "người chưa có kinh nghiệm",
    "chiếu mới": "người mới",
    "gato": "ghen tị",
    "xin vía": "xin may mắn",
    "nhả vía": "chia sẻ may mắn",
    "trộm vía": "may mắn",
    "cơm chó": "cảnh tình cảm",
    "cẩu lương": "cảnh tình cảm",
    "pha ke": "giả",
    "fake": "giả",
    "real": "thật",
    "riêu": "thật",
    "chầm cảm": "trầm cảm",
    "xỉu up xỉu down": "ngất lên ngất xuống",
    "xỉu ngang": "bất ngờ quá",
    "té ghế": "ngã ngửa",
    "hú hồn chim én": "giật cả mình",
    "hú hồn": "giật mình",
    "thót tim": "sợ hãi",
    "đứng hình": "ngạc nhiên",
    "rén": "sợ",
    "rén ngang": "sợ đột ngột",
    "toang": "hỏng",
    "toang rồi": "hỏng rồi",
    "bay màu": "biến mất",
    "bay acc": "mất tài khoản",
    "bay nick": "mất tài khoản",
    "ra đảo": "bị khóa tài khoản",
    "lót dép hóng": "chờ đợi",
    "hóng": "chờ đợi",
    "hóng drama": "xem chuyện thị phi",
    "hít drama": "hóng chuyện",
    "drama": "vụ việc ồn ào",
    "phốt": "bê bối",
    "bóc phốt": "vạch trần",
    "bú fame": "lợi dụng sự nổi tiếng",
    "ké fame": "lợi dụng sự nổi tiếng",
    "hám fame": "ham nổi tiếng",
    "sống ảo": "khoe khoang",
    "cà khịa": "mỉa mai",
    "cà chớn": "nghịch ngợm",
    "trẻ trâu": "trẻ con nghịch ngợm",
    "sửu nhi": "trẻ con nghịch ngợm",
    "nhạt": "không vui",
    "mặn": "thú vị",
    "mặn mòi": "thú vị",
    "nhạt toẹt": "chán phèo",
    "nhạt thếch": "chán ngắt",
    "khog": "không",
    "kg": "không",
    "hem": "không",
    "hum": "không",
    "dc hok": "được không",
    "đc ko": "được không",
    "dậy": "vậy",
    "dạ": "vâng",
    "ji": "gì",
    "j z": "gì vậy",
    "gì z": "gì vậy",
    "làm j": "làm gì",
    "lm j": "làm gì",
    "nta": "người ta",
    "nt": "nhắn tin",
    "seen": "đã xem",
    "pn": "bạn",
    "ox": "chồng",
    "bx": "vợ",
    "cr": "người mình thích",
    "crush": "người mình thích",
    "ex": "người yêu cũ",
    "thic": "thích",
    "yeu": "yêu",
    "y": "yêu",
    "wá": "quá",
    "un": "luôn",
    "ròi": "rồi",
    "oy": "rồi",
    "òy": "rồi",
    "hnay": "hôm nay",
    "nay": "này",
    "bjo": "bây giờ",
    "bjờ": "bây giờ",
    "h bao": "bao giờ",
    "đung": "đúng",
    "uh": "ừ",
    "uhm": "ừ",
    "um": "ừ",
    "ừm": "ừ",
    "ờ": "ừ",
    "g9": "ngủ ngon",
    "pp": "tạm biệt",
    "bai": "tạm biệt",
    "bye": "tạm biệt",
    "mng": "mọi người",
    "all": "mọi người",
    "mnguoi": "mọi người",
    "seo": "sao",
    "xao": "sao",
    "vcl": "vãi cả l**",
    "vcc": "vãi cả c**",
    "dm": "địt mẹ",
    "đcm": "địt con mẹ",
    "vailon": "vãi l**",
    "đéo": "không",
    "đ*o": "đéo",
    "đếch": "không",
    "đéch": "không",
    "cmn": "con mẹ nó",
    "cm": "con mẹ",
    "mịa": "mẹ",
    "mé": "mẹ",
    "má": "mẹ",
    "moẹ": "mẹ",
    "thoy": "thôi",
    "thoi": "thôi",
    "hoy": "thôi",
    "hihi": "cười",
    "hí hí": "cười",
    "haha": "cười",
    "kaka": "cười",
    "kk": "cười",
    "hix": "khóc",
    "oa oa": "khóc",
    "thế lày": "thế này",
    "dư lày": "như này",
    "như v": "như vậy",
    "như z": "như vậy",
    "zậy hả": "vậy hả",
    "z hả": "vậy hả",
    "thiệt": "thật",
    "thặc": "thật",
    "vđ": "vãi đạn",
    "klq": "không liên quan",
    "fl": "theo dõi",
    "sub": "đăng ký",
    "share": "chia sẻ",
    "like": "thích",
    "tym": "tim",
    "tha thu": "hình xăm",
    "tatto": "hình xăm",
    "bỉm sữa": "nuôi con",
    "mẹ bỉm": "mẹ nuôi con nhỏ",
    "bầu bì": "mang thai",
    "xịt keo": "cứng họng",
    "xịt keo cứng ngắc": "không nói nên lời",
    "sượng trân": "ngượng ngùng",
    "quê chữ ê kéo dài": "quê quá",
    "mắc cỡ onl": "xấu hổ giùm",
    "cứng ng": "đứng hình",
    "nhức nách": "tuyệt vời",
    "hết nước chấm": "quá tuyệt vời",
    "mlem mlem": "ngon quá",
    "mlem": "ngon",
    "bánh cuốn": "hấp dẫn",
    "cuốn": "hấp dẫn",
    "dính": "hay",
    "thao túng tâm lý": "điều khiển",
    "red flag": "cờ đỏ cảnh báo",
    "green flag": "cờ xanh an toàn",
    "check var": "kiểm tra/đối chiếu thông tin",
    "var": "kiểm tra",
    "quay xe": "đổi ý bất ngờ",
    "lật mặt": "phản bội",
    "ra dẻ": "ra vẻ",
    "phông bạt": "khoe khoang giả tạo",
    "flex": "khoe khoang",
    "bạch liên hoa": "giả tạo",
    "trà xanh": "người thứ ba",
    "tiểu tam": "người thứ ba",
    "tuesday": "người thứ ba",
    "con giáp thứ 13": "người thứ ba",
    "cắm sừng": "phản bội",
    "mọc sừng": "bị phản bội",
    "đổ vỏ": "nuôi con người khác",
    "đào mỏ": "lợi dụng tiền bạc",
    "hảo hán": "người giỏi",
    "hảo huynh đệ": "bạn tốt",
    "anh hùng bàn phím": "kẻ chỉ trích trên mạng",
    "tay nhanh hơn não": "bình luận thiếu suy nghĩ",
    "giang cư mận": "cư dân mạng",
    "cđm": "cộng đồng mạng",
    "netizen": "cư dân mạng",
    "thám tử online": "người soi mói",
    "camera chạy bằng cơm": "người hóng chuyện",
    "bà tám": "người nhiều chuyện",
    "chim lợn": "kẻ mách lẻo",
    "kỳ đà cản mũi": "kẻ cản trở",
    "bóng đèn": "người làm phiền cặp đôi",
    "ga tô": "ghen tị",
    "tóp tóp": "tiktok",
    "phờ bò": "facebook",
    "phở bò": "facebook",
    "fb": "facebook",
    "ytb": "youtube",
    "iu túp": "youtube",
    "zalo": "zalo",
    "ins": "instagram",
    "ig": "instagram",
    "chị gg": "google",
    "bác gg": "google",
    "soái ca": "trai đẹp",
    "nam thần": "trai đẹp",
    "nữ thần": "gái xinh",
    "hot boy": "trai đẹp",
    "hot girl": "gái xinh",
    "idol": "thần tượng",
    "ai đồ": "thần tượng",
    "fan cứng": "người hâm mộ trung thành",
    "anti fan": "người ghét",
    "ném đá": "chỉ trích",
    "gạch đá": "chỉ trích",
    "chhh": "chưa",
    "chx": "chưa",
    "nhg": "nhưng",
    "cũm": "cũng",
    "mò": "mà",
    "trùi": "trời",
    "chời": "trời",
    "bơ": "phớt lờ",
    "thính": "lời tán tỉnh",
    "thả thính": "tán tỉnh",
    "dính thính": "bị tán tỉnh",
    "đớp thính": "bị tán tỉnh",
    "m.n": "mọi người",
    "đăng xuất": "chết",
    "lên bảng đếm số": "chết",
    "bóc lịch": "đi tù",
    "ăn cơm nhà nước": "đi tù",
    "nhập kho": "đi tù",
    "lên dĩa": "bị phạt",
    "lên thớt": "bị phạt",
    "dựa cột": "bị xử bắn",
    "tào tháo rượt": "đau bụng",
    "mát nịt": "mất nết",
    "còn cái nịt": "mất hết không còn gì",
    "vua lì đòn": "người rất lì",
    "tởn tới già": "sợ đến già",
    "lỏ": "tệ",
    "báo đời": "phá hoại",
    "báo cha báo mẹ": "phá hoại cha mẹ",
    "mãi đỉnh": "tuyệt vời",
    "chất": "ngầu",
    "xịn sò": "tốt",
    "ảo ma": "ảo diệu",
    "ảo ma canada": "quá ảo/khó tin",
    "ét ô ét": "cứu với",
    "ố dề": "lố bịch",
    "quay xe khét lẹt": "đổi ý bất ngờ",
    "đi vào lòng đất": "tệ hại",
    "cú twist": "bất ngờ",
    "ngã ngửa": "bất ngờ",
    "trắng án": "vô tội",
    "xanh cỏ": "chết",
    "ngắm gà khỏa thân": "chết",
    "đi bán muối": "chết",
    "về với ông bà": "chết",
    "liệm": "chết",
    "hẹo": "chết",
    "nát": "hỏng",
    "báo": "phá hoại",
    "nghịch tử": "con hư",
    "báo nhà": "phá hoại gia đình",
    "gánh còng lưng": "chịu đựng thay",
    "gánh team": "gánh vác cả nhóm",
    "họa vô đơn chí": "xui xẻo liên tiếp",
    "dừa lòng t lắm": "vừa lòng tao lắm",
    "vừa lòng hả dạ": "thỏa mãn",
    "nghiệp quật": "gặp quả báo",
    "luật hoa quả": "luật nhân quả",
    "nhục mặt": "xấu hổ",
    "đội quần": "xấu hổ",
    "quê": "xấu hổ",
    "giả trân": "giả tạo",
    "dẫn sói vào nhà": "rước họa vào thân",
    "lùa gà": "lừa đảo người nhẹ dạ",
    "lùa": "lừa",
    "câu view": "thu hút lượt xem",
    "hóng biến": "chờ đợi tin tức hot",
    "cre": "nguồn",
    "nguồn": "nguồn",
    "in4": "info",
    "xin in4": "xin thông tin liên hệ",
    "info": "thông tin",
    "full": "đầy đủ",
    "demo": "nháp",
    "vlog": "video nhật ký",
    "clip": "video",
    "vid": "video",
    "block": "chặn",
    "unfollow": "hủy theo dõi",
    "follow": "theo dõi",
    "view": "lượt xem",
    "top": "đứng đầu",
    "top 1": "số 1",
    "đỉnh": "tuyệt vời",
    "ngầu lòi": "rất ngầu",
    "xịn": "tốt",
    "khét lẹt": "ghê gớm",
    "gắt": "ghê gớm",
    "chiến": "mạnh mẽ",
    "máu chiến": "hung hăng",
    "yang hồ": "giang hồ",
    "khứa": "hắn",
    "thằng chả": "hắn",
    "mụ nội": "bà nội",
    "con sen": "người hầu (chăm thú cưng)",
    "hoàng thượng": "mèo",
    "boss": "thú cưng",
    "f.a": "độc thân",
    "ế": "độc thân",
    "nóc nhà": "vợ/người yêu (nữ)",
    "cột nhà": "chồng/người yêu (nam)",
    "cá mập": "người giàu/nhà đầu tư",
    "cá con": "người mới/nhà đầu tư nhỏ",
    "áp bồ": "apple",
    "táo": "apple",
    "bro mã": "pro max",
    "ip": "iphone",
    "ai phôn": "iphone",
    "sam sung": "samsung",
    "android": "android",
    "ios": "ios",
    "mic": "micro",
    "cam": "camera",
    "app": "ứng dụng",
    "link": "đường dẫn",
    "acc": "tài khoản",
    "nick": "tài khoản",
    "pass": "mật khẩu",
    "hack": "xâm nhập",
    "lag": "giật",
    "bug": "lỗi",
    "game": "trò chơi",
    "map": "bản đồ",
    "skin": "trang phục (game)",
    "skill": "kỹ năng",
    "team": "đội",
    "gank": "hỗ trợ (game)/bắt quả tang",
    "solo": "đấu tay đôi",
    "pk": "đấu nhau",
    "combat": "trận chiến",
    "farm": "kiếm tiền (game)",
    "feed": "chơi tệ (game)",
    "afk": "treo máy",
    "gg": "đầu hàng",
    "gà": "chơi kém",
    "pro": "chơi giỏi",
    "vip": "người quan trọng",
    "member": "thành viên",
    "admin": "quản trị viên",
    "mem": "thành viên",
    "gr": "nhóm",
    "group": "nhóm",
    "page": "trang",
    "fanpage": "trang người hâm mộ",
    "sộp pe": "shopee",
    "laz": "lazada",
    "tiki": "tiki",
    "ship": "giao hàng",
    "shipper": "người giao hàng",
    "bom hàng": "bùng hàng",
    "bùng": "không trả tiền/không đến",
    "cod": "thanh toán khi nhận hàng",
    "bank": "chuyển khoản",
    "mom": "mẹ",
    "dad": "bố",
    "bro": "anh bạn",
    "sis": "chị/em gái",
    "baby": "cưng",
    "bae": "cưng",
    "chuppy": "mập mạp",
    "giế.t": "giết",
    "chế.t": "chết",
    "c.hặn": "chặn",
    "đ.ánh": "đánh",
    "hãm l**": "tệ hại/khó chịu",
    "hãm": "tệ hại",
    "vc": "vãi cả",
    "vờ lờ": "vãi l**",
    "đkm": "địt con mẹ",
    "mị": "mình",
    "tui": "tôi",
    "ce": "chị em",
    "gd": "gia đình",
    "gđ": "gia đình",
    "ms": "mới",
    "ye": "vâng",
    "yep": "đúng",
    "no": "không",
    "nope": "không",
    "ok": "được",
    "oki": "được",
    "oke": "được",
    "ukie": "được",
    "ws": "với",
    "gấc": "rất",
    "c3": "cấp 3",
    "ziền": "tiền",
    "tt": "tương tác",
    "stt": "status",
    "avt": "avatar",
    "vãi": "kinh ngạc",
    "vãi chưởng": "kinh ngạc",
    "vãi lúa": "kinh ngạc",
    "trầm cảm": "buồn bã",
    "tới công chuyện": "có chuyện hay/có biến",
    "hay ra dẻ quá": "hay ra vẻ quá",
    "mất não": "ngu ngốc",
    "não cá vàng": "hay quên",
    "người chơi hệ": "người thuộc nhóm",
    "gen z": "thế hệ z",
    "2k": "sinh năm 2000 trở đi",
    "roi": "rồi",
    "mjk": "mình",
    "fan": "người hâm mộ",
    "anti": "người ghét",
    "thuong": "thương",
    "nhu": "như",
    "qua": "quá",
    "nch": "nói chuyện",
    "nc": "nói chuyện",
    "chs": "chơi",
    "trc": "trước",
    "đth": "điện thoại",
    "tv": "tivi",
    "vd": "ví dụ",
    "thg": "thằng",
    "cl": "cái l**",
    "cmnr": "con mẹ nó rồi",
    "biến": "sự cố",
    "adiđàphật": "a di đà phật",
    "checkkk": "kiểm tra",
    "postcast": "podcast",
    "tbt": "tổng bí thư",
    "dảng": "đảng",
    "bâu": "bầu",
    "mo": "mơ",
    "m n": "mọi người",
    "lâm ly": "lâm lên",
    "dang": "đảng",
    "khong": "không",
    "duoc": "được",
    "biet": "biết",
    "nhung": "nhưng",
    "nguoi": "người",
    "con": "con",
    "em": "em",
    "anh": "anh",
    "chi": "chị",
    "tao": "tao",
    "may": "mày",
    "mong": "mong",
    "xe": "xe",
    "xem": "xem",
    "muon": "muốn",
    "mun": "muốn",
    "lam": "làm",
    "vao": "vào",
    "vo": "vào",
    "day": "đây",
    "nam": "năm",
    "a di": "a di đà phật",
    "nam mo": "nam mô",
    "y chang": "y chang",
    "tin dc": "tin được",
    "ko sao": "không sao",
    "ko bao": "không bao giờ",
    "a trai": "anh trai",
    "thg cha": "thằng cha",
    "ting ting": "tiếng tin nhắn/tiền về",
    "anh em": "anh em",
    "i want": "tôi muốn",
    "my life": "cuộc đời tôi",
    "my fault": "lỗi của tôi",
    "cam on": "cảm ơn",
    "tks": "cảm ơn",
    "thanks": "cảm ơn",
    "thank": "cảm ơn",
    "sr": "xin lỗi",
    "srr": "xin lỗi",
    "sorry": "xin lỗi",
    "chuc": "chúc",
    "hp": "hạnh phúc",
    "happy birthday": "chúc mừng sinh nhật",
    "cmsn": "chúc mừng sinh nhật",
    "hpbd": "chúc mừng sinh nhật",
    "iu thuong": "yêu thương",
    "ge": "ghê",
    "ghe": "ghê",
    "bv": "bệnh viện",
    "pl": "pháp luật",
    "đt": "điện thoại",
    "dt": "điện thoại",
    "xh": "xã hội",
    "a": "anh",
    "zai": "trai",
    "nx": "nữa",
    "mong gia": "mong gia đình",
    "mxh": "mạng xã hội",
    "stk": "số tài khoản",
    "cpn": "con",
    "bm": "bố mẹ",
    "zữ": "dữ",
    "review": "đánh giá",
    "comeback": "trở lại",
    "unsubcribe": "hủy đăng ký",
    "unsub": "hủy đăng ký",
    "tl": "trả lời",
    "bủh": "bro",
    "dảk": "dark",
    "lmao": "cười muốn rớt hàm",
    "hieuthuhai": "hiếu thứ hai",
    "tq": "trung quốc",
    "l": "l**",
    "hoa sen": "tập đoàn hoa sen",
    "con trai": "con trai",
    "cao to": "cao to",
    "ko ai": "không ai",
    "k co": "không có",
    "k phai": "không phải",
    "k dam": "không dám",
    "k biet": "không biết",
    "k tin": "không tin",
    "skibidi": "skibidi",
    "visual": "ngoại hình",
    "creepy": "đáng sợ",
    "omg": "trời ơi",
    "mv": "video ca nhạc",
    "yo bae": "yo bae",
    "hs": "học sinh",
    "đg": "đang",
    "ik": "đi",
    "t rén": "tao sợ",
    "j v": "gì vậy",
    "ủa j z": "ủa gì vậy",
    "z tr": "vậy trời",
    "v tr": "vậy trời",
    "sao v tr": "sao vậy trời",
    "nhìn k ra": "nhìn không ra",
    "quá tr": "quá trời",
    "đúng k": "đúng không",
    "đc k": "được không",
    "nha mng": "nha mọi người",
    "nha mn": "nha mọi người",
    "tin chuẩn chưa z pa": "tin chuẩn chưa vậy ba",
    "đâu pk": "đâu phải",
    "bt r": "biết rồi",
    "đc r": "được rồi",
    "đúng r": "đúng rồi",
    "xong r": "xong rồi",
    "thôi r": "thôi rồi",
    "mệt ngang": "mệt mỏi đột ngột",
    "đứng tim": "hoảng sợ tột độ",
    "rụng tim": "giật mình",
    "hồn vía lên mây": "vô cùng hoảng sợ",
    "quay xe gấp": "thay đổi ý định ngay lập tức",
    "bó tay": "không thể hiểu nổi",
    "đến chịu": "không thể hiểu nổi/chịu thua",
    "cạn lời": "không còn gì để nói",
    "chán ko buồn nói": "quá chán không muốn nói nữa",
    "ko nói nên lời": "không thể nói gì vì quá sốc",
    "hết sẩy": "tuyệt vời",
    "nhức cái đầu": "rất mệt mỏi/phiền phức",
    "hãm tài": "tệ hại/xui xẻo",
    "đúng là mắt ko thấy tim ko đau": "không biết thì không buồn",
    "tù mọt gông": "đi tù rất lâu",
    "gô cổ": "bắt giữ",
    "mặt lưỡi cày": "khuôn mặt có cằm dài/nhọn",
    "mê chữ ê kéo dài": "cực kỳ thích",
    "đứng hình mất 5 giây": "vô cùng bất ngờ",
    "mắt chữ a mồm chữ o": "ngạc nhiên tột độ",
    "tốn cơm tốn gạo": "vô dụng",
    "oan gia ngõ hẹp": "gặp người không muốn gặp",
    "biến căng": "vụ việc nghiêm trọng",
    "ảo tung chảo": "quá vô lý",
    "dắt mũi": "điều hướng dư luận sai lệch",
    "ăn bánh vẽ": "bị lừa bởi lời hứa suông",
    "snhat": "sinh nhật",
    "hsk5": "hán ngữ bậc 5",
    "hrntai": "phim người lớn",
    "của ló": "của nó",
    "tin dc k": "tin được không",
    "ủa alo": "ủa gì vậy",
    "hả tr": "hả trời",
    "hết r": "hết rồi",
    "ko bt": "không biết",
    "k bt": "không biết",
    "k dám": "không dám",
    "k có": "không có",
    "k phải": "không phải",
    "lun á": "luôn á",
    "t mún": "tao muốn",
    "t coi": "tao coi",
    "t thấy": "tao thấy",
    "hãm l": "hãm",
    "vãi t": "vãi thật",
    "sợ vkl": "rất sợ",
    "gian thương": "người buôn bán gian lận",
    "láng giềng": "hàng xóm",
    "da gà": "nổi da gà",
    "thốt tim": "sợ hãi",
    "nam mô": "nam mô",
    "mô a": "mô a di đà",
    "tôn hoa": "tôn hoa sen",
    "trung tâm": "cơ sở/trường học",
    "công an": "cảnh sát",
    "việt nam": "việt nam",
    "tức cành hông": "rất tức giận",
    "vừa rén vừa ghiền": "vừa sợ vừa thích",
    "rén ngang xương": "đột nhiên rất sợ",
    "cười muốn sản": "cười đến mức phát điên",
    "són ra quần": "vô cùng sợ hãi",
    "lạnh sống lưng": "rất đáng sợ",
    "thốn dùm": "cảm thấy đau thay",
    "nhột dùm": "cảm thấy hổ thẹn/bị chạm lòng tự ái thay",
    "sém đi theo ông bà": "suýt chết",
    "vô đạo bất lương": "tệ hại",
    "sống chó": "tệ bạc",
    "flo chéo": "theo dõi qua lại",
    "follow chéo": "theo dõi qua lại",
    "idol lỏ": "thần tượng tệ",
    "fifai": "game free fire",
    "hết kn": "hết khả năng",
    "thk": "thằng",
    "oánh": "đánh",
    "bêu tên": "công khai tên để chỉ trích",
    "nhớ nhươn": "nhớ thương",
    "vấn vươn": "vấn vương",
    "sém": "suýt",
    "răng đe": "răn đe",
    "nghèo rân": "người dân nghèo",
    "khồ ơn": "khổ hơn",
    "ông hoàng bếp núc": "người nấu ăn giỏi (hoặc mỉa mai)",
    "chúa tể bóng đêm": "biệt danh vui vẻ/mỉa mai",
    "flag hạng nặng": "cảnh báo nguy hiểm cao",
    "lội sông": "ngập lụt nặng",
    "đắp chiếu": "đã chết",
    "hồi quang phản chiếu": "dấu hiệu cuối cùng trước khi mất"
}